yaunqi_plugin_mcp/__init__.py
yaunqi_plugin_mcp/__main__.py
yaunqi_plugin_mcp/server.py
url2qrcode-0.1.1.dist-info/METADATA
url2qrcode-0.1.1.dist-info/WHEEL
url2qrcode-0.1.1.dist-info/entry_points.txt
url2qrcode-0.1.1.dist-info/RECORD
