Metadata-Version: 2.4
Name: url2qrcode
Version: 0.1.1
Summary: mcp server to change url to qrcode
Author-email: rodneyxiong <rodneyxiong@tencent.com>
Keywords: mcp,qrcode
Classifier: Development Status :: 4 - Beta
Classifier: Intended Audience :: Developers
Classifier: License :: OSI Approved :: MIT License
Classifier: Programming Language :: Python :: 3
Classifier: Programming Language :: Python :: 3.10
Classifier: Programming Language :: Python :: 3.11
Classifier: Programming Language :: Python :: 3.12
Classifier: Programming Language :: Python :: 3.13
Requires-Python: >=3.10
Requires-Dist: httpx>=0.28.1
Requires-Dist: mcp>=1.7.1
Requires-Dist: qrcode[pil]>=8.2
